README.rst
setup.py
pycydemo/__init__.py
pycydemo/extension.pyx
pycydemo/version.py
pycydemo.egg-info/PKG-INFO
pycydemo.egg-info/SOURCES.txt
pycydemo.egg-info/dependency_links.txt
pycydemo.egg-info/not-zip-safe
pycydemo.egg-info/requires.txt
pycydemo.egg-info/top_level.txt
pycydemo/tests/__init__.py
pycydemo/tests/test_extension.py