Metadata-Version: 1.0
Name: pycydemo
Version: 0.3.4
Summary: Demo python+cython project
Home-page: https://github.com/theochem/python-cython-ci-example
Author: Toon Verstraelen
Author-email: Toon.Verstraelen@UGent.be
License: UNKNOWN
Platform: UNKNOWN
